pytest_pilot/__init__.py
pytest_pilot/_version.py
pytest_pilot/new_hooks.py
pytest_pilot/plugin.py
pytest_pilot/py.typed
pytest_pilot/pytest_compat.py
pytest_pilot/pytest_marks.py
pytest_pilot/test_doc/__init__.py
pytest_pilot/test_doc/extender_noarg/__init__.py
pytest_pilot/test_doc/extender_noarg/conftest.py
pytest_pilot/test_doc/extender_noarg/test_extender.py
pytest_pilot/test_doc/hardfilter_arg/__init__.py
pytest_pilot/test_doc/hardfilter_arg/conftest.py
pytest_pilot/test_doc/hardfilter_arg/test_hardfilter.py
pytest_pilot/test_doc/params/__init__.py
pytest_pilot/test_doc/params/conftest.py
pytest_pilot/test_doc/params/test_params.py
pytest_pilot/test_doc/silos_arg/__init__.py
pytest_pilot/test_doc/silos_arg/conftest.py
pytest_pilot/test_doc/silos_arg/test_silos.py
pytest_pilot/test_doc/silos_noarg/__init__.py
pytest_pilot/test_doc/silos_noarg/conftest.py
pytest_pilot/test_doc/silos_noarg/test_silos.py
pytest_pilot/test_doc/softfilter_arg/__init__.py
pytest_pilot/test_doc/softfilter_arg/conftest.py
pytest_pilot/test_doc/softfilter_arg/test_softfilter.py
pytest_pilot-0.8.0.dist-info/LICENSE
pytest_pilot-0.8.0.dist-info/METADATA
pytest_pilot-0.8.0.dist-info/WHEEL
pytest_pilot-0.8.0.dist-info/entry_points.txt
pytest_pilot-0.8.0.dist-info/top_level.txt
pytest_pilot-0.8.0.dist-info/RECORD
