Metadata-Version: 2.1
Name: pytest-pilot
Version: 0.8.0
Summary: Slice in your test base thanks to powerful markers.
Home-page: https://github.com/smarie/python-pytest-pilot
Maintainer: Sylvain MARIE
Maintainer-email: sylvain.marie@schneider-electric.com
License: BSD 3-Clause
Download-URL: https://github.com/smarie/python-pytest-pilot/tarball/0.8.0
Keywords: pytest test mark marker slice query filter command option
Platform: UNKNOWN
Classifier: Development Status :: 5 - Production/Stable
Classifier: Intended Audience :: Developers
Classifier: Topic :: Software Development :: Testing
Classifier: License :: OSI Approved :: BSD License
Classifier: Programming Language :: Python :: 2.7
Classifier: Programming Language :: Python :: 3.5
Classifier: Programming Language :: Python :: 3.6
Classifier: Programming Language :: Python :: 3.7
Classifier: Framework :: Pytest
Requires-Dist: enum34 ; python_version < "3.4"
